CHANGES.rst
CONTRIBUTORS.rst
MANIFEST.in
README.rst
setup.cfg
setup.py
collective/.DS_Store
collective/__init__.py
collective.suisseid.egg-info/PKG-INFO
collective.suisseid.egg-info/SOURCES.txt
collective.suisseid.egg-info/dependency_links.txt
collective.suisseid.egg-info/namespace_packages.txt
collective.suisseid.egg-info/not-zip-safe
collective.suisseid.egg-info/requires.txt
collective.suisseid.egg-info/top_level.txt
collective/suisseid/.DS_Store
collective/suisseid/README.rst
collective/suisseid/__init__.py
collective/suisseid/configure.zcml
collective/suisseid/setuphandlers.py
collective/suisseid/portlets/__init__.py
collective/suisseid/portlets/configure.zcml
collective/suisseid/portlets/login.pt
collective/suisseid/portlets/login.py
collective/suisseid/profiles/default/.DS_Store
collective/suisseid/profiles/default/metadata.xml
collective/suisseid/profiles/default/portlets.xml
collective/suisseid/profiles/default/suisseid-pas.txt
collective/suisseid/resources/suisseid.png
collective/suisseid/tests/__init__.py
collective/suisseid/tests/test_installation.py